CHANGELOG.txt
LICENCE.txt
MANIFEST.in
README.txt
setup.py
backtrader/__init__.py
backtrader/backtrader.py
backtrader/broker.py
backtrader/config.py
backtrader/feed.py
backtrader/position.py
backtrader/reference.py
backtrader/report.py
backtrader/store.py
backtrader/strategy.py
backtrader/utils.py
example/main.py
pantuchy_backtrader.egg-info/PKG-INFO
pantuchy_backtrader.egg-info/SOURCES.txt
pantuchy_backtrader.egg-info/dependency_links.txt
pantuchy_backtrader.egg-info/requires.txt
pantuchy_backtrader.egg-info/top_level.txt