Metadata-Version: 2.1
Name: pantuchy-backtrader
Version: 1.0.3
Summary: Backtesting library.
Home-page: https://github.com/pantuchy/backtrader
Author: Maksim Pol
Author-email: p.m.n@outlook.com
License: MIT
Keywords: backtesting
Classifier: Development Status :: 5 - Production/Stable
Classifier: Intended Audience :: Education
Classifier: Operating System :: Microsoft :: Windows :: Windows 10
Classifier: License :: OSI Approved :: MIT License
Classifier: Programming Language :: Python :: 3
Requires-Python: >=3.8
License-File: LICENCE.txt
